wsgi_objgraph-0.1.dist-info/DESCRIPTION.rst
wsgi_objgraph-0.1.dist-info/METADATA
wsgi_objgraph-0.1.dist-info/RECORD
wsgi_objgraph-0.1.dist-info/WHEEL
wsgi_objgraph-0.1.dist-info/entry_points.txt
wsgi_objgraph-0.1.dist-info/metadata.json
wsgi_objgraph-0.1.dist-info/top_level.txt
wsgiobjgraph/__init__.py
wsgiobjgraph/paste.py
