Metadata-Version: 2.0
Name: wsgi-objgraph
Version: 0.1
Summary: wsgi middleware for objgprah
Home-page: https://github.com/aodag/wsgi-objgraph
Author: Atsushi Odagiri
Author-email: aodagx@gmail.com
License: MIT
Platform: UNKNOWN
Requires-Dist: objgraph
Provides-Extra: dev
Requires-Dist: webob; extra == 'dev'
Requires-Dist: waitress; extra == 'dev'
Requires-Dist: pastescript; extra == 'dev'
Provides-Extra: testing
Requires-Dist: pytest; extra == 'testing'
Requires-Dist: pytest-cov; extra == 'testing'
Requires-Dist: webtest; extra == 'testing'
